Metadata-Version: 1.1
Name: compact-consistencyReg
Version: 0.0.4
Summary: API that provides methods to construct deep compact classification models using semi-supervised methods.
Home-page: https://github.com/adines/SOTA-tinyML
Author: Adrian Ines
Author-email: adines@unirioja.es
License: UNKNOWN
Keywords: classification,compact networks,deep learning,semi-supervised
Platform: UNKNOWN
Classifier: Development Status :: 4 - Beta
Classifier: Intended Audience :: Developers
Classifier: Topic :: Software Development :: Build Tools
Classifier: License :: OSI Approved :: MIT License
Classifier: Programming Language :: Python :: 3.6
